flamingo/Flamingo.py
flamingo/__init__.py
flamingo_histology-0.1.2.dist-info/LICENSE.md
flamingo_histology-0.1.2.dist-info/METADATA
flamingo_histology-0.1.2.dist-info/WHEEL
flamingo_histology-0.1.2.dist-info/top_level.txt
flamingo_histology-0.1.2.dist-info/RECORD
