Metadata-Version: 2.1
Name: flamingo-histology
Version: 0.1.2
Summary: Flamingo: a package for extracting and exporting annotations from H&E images
Author-email: J S McKenzie <jsmckenzi@users.noreply.github.com>
Project-URL: Homepage, https://jsmckenzie.github.io/flamingo/index.html/
Project-URL: Bug Tracker, https://jsmckenzie.github.io/flamingo/index.html
Project-URL: Documentation, https://jsmckenzie.github.io/flamingo/index.html
Classifier: Programming Language :: Python :: 3.10
Classifier: License :: OSI Approved :: MIT License
Classifier: Operating System :: OS Independent
Classifier: Topic :: Scientific/Engineering :: Bio-Informatics
Classifier: Topic :: Scientific/Engineering :: Image Processing
Requires-Python: >=3.10
License-File: LICENSE.md
